[
    {
        "title": "حکایت شمارهٔ ۱ باب چهارم",
        "prose": [
            "یکی را از دوستان گفتم: امتناع سخن گفتنم به علّتِ آن اختیار آمده است در غالبِ اوقات، که در سخنْ نیک و بد اتّفاق افتد و دیدهٔ دشمنان جز بر بدی نمی‌آید.",
            "گفت: دشمن آن به که نیکی نبیند."
        ],
        "verses": [
            {
                "verse1": "وَ اَخُو الْعَداوَةِ لا یَمُرُّ بِصالِحٍ",
                "verse2": "اِلّا وَ یَلْمُزُهُ بِکَذّابٍ اَشِرْ"
            },
            {
                "verse1": "هنر به چشم عداوت بزرگتر عیب است",
                "verse2": "گل است سعدی و در چشم دشمنان خار است"
            },
            {
                "verse1": "نورِ گیتی‌فروزِ چشمهٔ هور",
                "verse2": "زشت باشد به چشمِ موشکِ کور"
            }
        ]
    }
]